Metadata-Version: 1.1
Name: python-telegram-logger
Version: 1.3
Summary: Simple telegram logger
Home-page: https://github.com/porovozls/python-telegram-logger
Author: Dmytro Smyk
Author-email: porovozls@gmail.com
License: BSD License
Platform: UNKNOWN
Classifier: Intended Audience :: Developers
Classifier: License :: OSI Approved :: BSD License
Classifier: Operating System :: OS Independent
Classifier: Programming Language :: Python
Classifier: Programming Language :: Python :: 3.5
Classifier: Programming Language :: Python :: 3.6
Classifier: Topic :: Internet :: WWW/HTTP
Classifier: Topic :: Internet :: WWW/HTTP :: Dynamic Content
